longtext.py
longtext-0.0.1.dist-info/METADATA
longtext-0.0.1.dist-info/WHEEL
longtext-0.0.1.dist-info/top_level.txt
longtext-0.0.1.dist-info/RECORD
