Metadata-Version: 2.1
Name: longtext
Version: 0.0.1
Summary: Text line generator and repeater.
Home-page: UNKNOWN
Author: Akash.A
License: UNKNOWN
Platform: UNKNOWN
Classifier: Programming Language :: Python :: 3
Classifier: Operating System :: OS Independent
